shade_ms/__init__.py
shade_ms/__main__.py
shade_ms/dask_utils.py
shade_ms/data_mappers.py
shade_ms/data_plots.py
shade_ms/ds_ext.py
shade_ms/main.py
shade_ms/ms_info.py
shade_ms/tests/Makefile
shade_ms/tests/README.md
shade_ms/tests/__init__.py
shade_ms/tests/check-shadems-functionality.sh
shade_ms/tests/test_dask_utils.py
shadems-0.5.4.dist-info/METADATA
shadems-0.5.4.dist-info/WHEEL
shadems-0.5.4.dist-info/entry_points.txt
shadems-0.5.4.dist-info/RECORD
