Metadata-Version: 2.3
Name: shadems
Version: 0.5.4
Summary: Rapid Measurement Set plotting with dask-ms and datashader
License: GPL-2.0-only
Keywords: Astronomy,Visualisation,Packaging
Author: Ian Heywood & RATT
Author-email: ian.heywood@physics.ox.ac.uk
Requires-Python: >=3.10,<3.13
Classifier: Development Status :: 4 - Beta
Classifier: Intended Audience :: Science/Research
Classifier: License :: OSI Approved :: GNU General Public License v2 (GPLv2)
Classifier: Operating System :: POSIX :: Linux
Classifier: Programming Language :: Python
Classifier: Programming Language :: Python :: 3
Classifier: Programming Language :: Python :: 3.10
Classifier: Programming Language :: Python :: 3.11
Classifier: Programming Language :: Python :: 3.12
Classifier: Topic :: Scientific/Engineering :: Astronomy
Provides-Extra: testing
Requires-Dist: cmasher (>=1.6.3,<2.0.0)
Requires-Dist: dask-ms[xarray] (>=0.2.20,<0.3.0) ; python_version < "3.12"
Requires-Dist: dask-ms[xarray] (>=0.2.23,<0.3.0) ; python_version >= "3.12"
Requires-Dist: datashader (>=0.16.0,<0.17.0)
Requires-Dist: future-fstrings (>=1.2.0,<2.0.0)
Requires-Dist: holoviews (>=1.20.0,<2.0.0)
Requires-Dist: matplotlib (>=3.9.4,<4.0.0)
Requires-Dist: pytest (>=7.2.2,<8.0.0) ; extra == "testing"
Requires-Dist: pytest-flake8 (>=1.1.1,<2.0.0) ; extra == "testing"
Requires-Dist: requests (>=2.27.1,<3.0.0)
Project-URL: Homepage, https://github.com/ratt-ru/shadeMS
Project-URL: Repository, https://github.com/ratt-ru/shadeMS
